{
  "label": "Species Traits",
  "entries": {
    "A Head for Knots": {
      "name": "매듭에 밝은 머리 - A Head for Knots"
    },
    "A Mean Right Hook": {
      "name": "매서운 오른손 훅 - A Mean Right Hook"
    },
    "A Mind Outside the Box": {
      "name": "틀을 벗어난 정신 - A Mind Outside the Box"
    },
    "Acid Breath": {
      "name": "산성 브레스 - Acid Breath",
      "description": "<section class=\"secret\"><p> [[lookup @details.type.config.label lowercase]] 타입은 직선으로 60ft, 5ft 너비 범위에 산성 물질을 뿜어냅니다. </p><p>해당하는 직선 범위에 있던 크리처는 각자 <strong>DC 18 민첩</strong> 내성 굴림을 하여 실패하면 <strong>54(12d8)점의 <em>산성 피해</em></strong>를 입고, 성공하면 그 절반의 피해를 입습니다. </p></section><p> [[lookup @details.type.config.label lowercase]] 타입은 직선으로 60ft, 5ft 너비 범위에 산성 물질을 뿜어냅니다. 해당하는 직선 범위에 있던 크리처는 각자 <strong>민첩</strong> 내성 굴림을 해야만 합니다.</p>"
    },
    "Armaments of the First": {
      "name": "Armaments 의 - First",
      "description": "<p><span style=\"font-family:Signika, sans-serif\">?? ???? ????? ???? ?? ?? ??? ????. ??? @UUID[Compendium.beast-world.species-traits.Item.PvMORczp5PEhrfwN]{Hoof Stomp}? @UUID[Compendium.beast-world.species-traits.Item.CI0i78FAZfxEV4MY]{뿔받기 - Gore} ??? ????(?? ???, ? ??? ??? ?????). ? ??? ??? ?? ???? 1d6?? ?? ??? ???. Hoof Stomp? ?? ???, Gore ??? ??? ??? ???.</span></p>"
    },
    "Better With an Audience": {
      "name": "Better With an 관객"
    },
    "Birthmates of the Arcana": {
      "name": "Birthmates 의 - Arcana"
    },
    "Body of Grace": {
      "name": "몸체 의 은총 - Body of Grace",
      "description": "<p>??? ?? ??? ?? ??? ????. 11??? ????, ??? ?? ?? ??? 19 ?? 20? ??? ???? ???.</p>"
    },
    "Bounding Grace": {
      "name": "Bounding 은총"
    },
    "Brittle Shieldscales": {
      "description": "<p style=\"box-sizing:border-box;user-select:text;--tw-translate-x:0;--tw-translate-y:0;--tw-rotate:0;--tw-skew-x:0;--tw-skew-y:0;--tw-scale-x:1;--tw-scale-y:1;--tw-scroll-snap-strictness:proximity;--tw-ring-offset-width:0px;--tw-ring-offset-color:#fff;--tw-ring-color:rgb(59 130 246 / 0.5);--tw-ring-offset-shadow:0 0 #0000;--tw-ring-shadow:0 0 #0000;--tw-shadow:0 0 #0000;--tw-shadow-colored:0 0 #0000;color:#191813;font-size:13px\">??? ???? ??? ??? ?? ???? ??? ?? ??? ????. ? ??? ?? ???, [[/r 5 * @prof]](?? ???? 5?)? ?? ??? ?? HP? ??, AC? +2 ???? ????.</p><p style=\"box-sizing:border-box;user-select:text;--tw-translate-x:0;--tw-translate-y:0;--tw-rotate:0;--tw-skew-x:0;--tw-skew-y:0;--tw-scale-x:1;--tw-scale-y:1;--tw-scroll-snap-strictness:proximity;--tw-ring-offset-width:0px;--tw-ring-offset-color:#fff;--tw-ring-color:rgb(59 130 246 / 0.5);--tw-ring-offset-shadow:0 0 #0000;--tw-ring-shadow:0 0 #0000;--tw-shadow:0 0 #0000;--tw-shadow-colored:0 0 #0000;color:#191813;font-size:13px\">?? ??? ??? ??? ??? ?? ???. ? ?? 4? ??? ??? ?? ?? ?????? ??? ?? ????. 11??? ???? ? ??? 6?? ?????. ?? HP?? ???? ? ??? AC ???? ???, ? ??? ?? ??? ?? ?? ????.</p>"
    },
    "Cheiropocket": {
      "description": "<p>?? ??? ?? ??? ?? ?? ???? ??? ??? ??? ????. ? ?????? ?? ?? ?? ?? ???? ??? ?????. ??? ???? ?? ??? ??? ?????? ??? ?? ?? ? ????. ?? ?? ???? ??? ???? ???? ??? ?? ???, ???? ??? ??? ?? ? ????.</p><p>??? ?????? ??? ?? ???? 12?? ???? ?? ????? ???? ?? ? ???, ?? 12 ?? ??? ???. ?? ?? ???? ?? ? ??? ??? ??, ??? ??? ??? ??? ?? ???? ?????. ??? ?? ???? ??? ??? ??? ?? ??? ????. HP? 0? ??? ??? ??? ? ???? ??? ??? ?? ?? ? ??? ??? ????.</p><p>??? ?? ???? ??? ?? ???? ????, ??? ????? ??? ??? ??? ? ????. ????? ???? ??, ??? ?????? ???? ? ???? ??? ? ?? ??? ????.</p>"
    },
    "Clumsy Competence": {
      "description": "<p>??? ??? ????? ??? ???? ?? ???? ??? ?? ??? ???? ?? ??? ????(??? ???? ???? ? ?????). ??? ?? ???? @UUID[Compendium.beast-world.species-traits.Item.xW0wE9YOwGwCuJm9]{Stackable Intellect} ?? ?? ???? ?? ?? ?? ?? ??? +1 ???? ????. ??? ?? ??? 9 ???? ? ???? +2? ???.</p>"
    },
    "Cold Breath": {
      "name": "냉기 브레스 - Cold Breath",
      "description": "<section class=\"secret\">\n<p>**냉기 브레스.**  [[lookup @details.type.config.label lowercase]]이/가 60ft의 원뿔형 범위에 얼어붙을 듯한 바람을 뿜어냅니다. 해당하는 범위에 있던 크리처는 각자 <strong>DC 20 건강</strong> 내성 굴림을 하여 실패하면 <strong>58(13d8)점의 <em>냉기 피해</em></strong>를 입고, 성공하면 그 절반의 피해를 입습니다.</p>\n</section>\n<p> [[lookup @details.type.config.label lowercase]]이/가 60ft의 원뿔형 범위에 얼어붙을 듯한 바람을 뿜어냅니다. 해당하는 범위에 있던 크리처는 각자 <strong>건강</strong> 내성 굴림을 해야만 합니다.</p>"
    },
    "Collective Magic": {
      "name": "Collective 마법"
    },
    "Contorted Breathing": {
      "description": "<p>??? ??? ?? ?? ??? ??? ???? ?? ? ????.</p><ul><li><em>Cove</em>. ?? ??? ??? ??? ??? ???? ????? ??? ? ????.</li><li><em>Volcano</em>. ??? ??? ???? ?? ??? ???? ??? ? ????.</li><li><em>Flatland</em>. ?? ??? ?? ??? ? ? ?? ? ????. ? ???? ? ?? ??? ? ?? ?? ? ????. </li><li><em>Glacier</em>. ?? ??? ????? ?? ?? ?? ?? ??? ???.</li></ul>"
    },
    "Crown and Scepter": {
      "name": "Crown 및 - Scepter"
    },
    "Darkvision": {
      "name": "암시야 - Darkvision"
    },
    "Dragon Magic (Bulwark)": {
      "name": "드래곤 마법 (Bulwark)"
    },
    "Dragon Magic (Dancing)": {
      "name": "드래곤 마법 (Dancing)",
      "description": "<p>? ???? @Compendium[dnd5e.spells.B0pnIcc52O6G8hi8]{Longstrider} ??? ?? ???? ?? ??? ? ????. 5??? ???? @UUID[Compendium.beast-world.spells.Item.rbb7LuJOGokbjP1t]{Perfect Respiration} ??? ? ???? ??? ? ????. ? ???? ? ? ?? ? ??? ????, ? ??? ?? ??? ?? ??? ?? ? ???? ??? ? ????. ?? ??? ??? ?? ??? ??? ? ? ?? ? ??? ??? ? ????. ? ???? ? ???? ??? ?, ??? ?? ?? ??? ?????.</p>"
    },
    "Dragon Magic (Monarch)": {
      "name": "드래곤 마법 (군주) - Dragon Magic (Monarch)",
      "description": "<p>? ???? @Compendium[dnd5e.spells.arzCrMRgcNiQuh43]{Command} ??? ??? ? ????. 5??? ???? @UUID[Compendium.beast-world.spells.Item.ggLjRmy42S54ceBX]{대상 소환 - Summon Subject} ??? ? ???? ??? ? ????. ? ???? ? ? ?? ? ??? ????, ? ??? ?? ??? ?? ??? ?? ? ???? ??? ? ????. ?? ??? ??? ?? ??? ??? ? ? ?? ? ??? ??? ? ????.</p><p>? ???? ? ???? ??? ?, ??? ?? ?? ??? ?????.</p>"
    },
    "Dragon Magic (Scholar)": {
      "name": "드래곤 마법 (학자) - Dragon Magic (Scholar)"
    },
    "Dragon Magic (Whispering)": {
      "name": "드래곤 마법 (속삭임) - Dragon Magic (Whispering)",
      "description": "<p><span class=\"fontstyle0\">? ???? @Compendium[dnd5e.spells.82jM6qD9axLJsTrH]{Illusory Script}</span><span class=\"fontstyle2\"> </span><span class=\"fontstyle0\">spell? ?? ???? ?? ??? ? ????. 5??? ???? </span><span class=\"fontstyle2\">@UUID[Compendium.beast-world.spells.Item.asx3NHiA0tNi51WX]{Discern the 심장's - Hoard} </span><span class=\"fontstyle0\">spell? ? ???? ??? ? ????. ? ???? ? ? ?? ? ??? ????, ? ??? ?? ??? ?? ??? ?? ? ???? ??? ? ????. ?? ??? ??? ?? ??? ??? ? ? ?? ? ??? ??? ? ????.</span></p><p><span class=\"fontstyle0\">? ???? ? ???? ??? ?, ??? ?? ?? ??? ?????. </span></p>"
    },
    "Eidetic Memory": {
      "name": "Eidetic 기억"
    },
    "Fire Breath": {
      "name": "화염 브레스 - Fire Breath",
      "description": "<section class=\"secret\">\n<p>**화염 브레스.**  [[lookup @details.type.config.label lowercase]]이/가 너비 5ft의 직선 60ft 범위에 화염을 뿜어냅니다. 해당하는 직선 범위에 있던 크리처는 각자 <strong>DC 18 민첩</strong> 내성 굴림을 하여 실패하면 <strong>45(13d6)점의 <em>화염 피해</em></strong>를 입고, 성공하면 그 절반의 피해를 입습니다.</p>\n</section>\n<p> [[lookup @details.type.config.label lowercase]]이/가 너비 5ft의 직선 60ft 범위에 화염을 뿜어냅니다. 해당하는 직선 범위에 있던 크리처는 각자 <strong>민첩</strong> 내성 굴림을 해야만 합니다.</p>"
    },
    "Gore": {
      "name": "뿔받기 - Gore"
    },
    "Head Down, Feet Forward": {
      "name": "Head Down, 발 - Forward"
    },
    "Hunter's Cleave": {
      "name": "사냥꾼's - Cleave"
    },
    "Inner Spark": {
      "description": "<p>??? ??? ???? ??? ?? ??? ? ????, ??? ??? ??? ??? ??? ??? ??? ? ????. ??? ????? ?? ??? ? ???, ? ???? ??? 1d4?? ?? ??? ????.</p>"
    },
    "Leftover Magic": {
      "name": "Leftover 마법",
      "description": "<p>?? ?? ?? ? ????, ? ??? ??? ???? ?????. ??? ? ? ?? 60?? ?? ????? ??? ???? ?? ?? ???? ??, ? ??? ??? ??? ??? 3?? ?? ? ????(?? 1??), ??? ??? ??? ? ??? ??? ????? ??? ??? ? ? ????. ? ??? ???? ? ??? ?? ??? ?? ??? ? ????.</p>"
    },
    "Life's Passion": {
      "name": "생명's - Passion",
      "description": "<p>??? ??? ??? ?? ??? ?? ??? ??, ?? ? ??? ??? ?? ??? ????: Arcana, History, Medicine, Nature, Religion. ? ? ??? ??? ?? ???? ?? ???? ? ?? ?????. ?? ?? ??? ?? ?? ?? ?? ??? ?? ??? ???, ? ??? ???? finesse ? thrown (range 20/60) ??? ?????.</p>"
    },
    "Lightning Breath": {
      "name": "번개 브레스 - Lightning Breath",
      "description": "<section class=\"secret\"><p> [[lookup @details.type.config.label lowercase]]이/가 5ft 너비의 90ft 직선 범위에 뇌전을 뿜어냅니다. 해당하는 직선 범위에 있던 크리처는 각자 <strong>DC 19 민첩</strong> 내성 굴림을 하여 실패하면 <strong>66(12d10)점의 <em>번개 피해</em></strong>를 입고, 성공하면 그 절반의 피해를 입습니다.</p><p></p></section><p> [[lookup @details.type.config.label lowercase]]이/가 5ft 너비의 90ft 직선 범위에 뇌전을 뿜어냅니다. 해당하는 직선 범위에 있던 크리처는 각자 <strong>민첩</strong> 내성 굴림을 해야만 합니다.</p>"
    },
    "Long Arms": {
      "name": "Long 무장"
    },
    "Low-Light Vision": {
      "name": "저조도 시야 - Low-Light Vision"
    },
    "Malleable Mind": {
      "name": "Malleable 정신"
    },
    "Masterpiece of Movement": {
      "name": "Masterpiece 의 - Movement"
    },
    "Mind for Beasts": {
      "name": "정신 - for Beasts"
    },
    "Mnemonic Mind": {
      "name": "Mnemonic 정신"
    },
    "Natural Armor (Armadillo)": {
      "name": "천연 갑옷 (아르마딜로) - Natural Armor (Armadillo)"
    },
    "Natural Armor (Dragon)": {
      "name": "천연 갑옷 (드래곤) - Natural Armor (Dragon)"
    },
    "Natural Weapons": {
      "name": "천연 무기 - Natural Weapons",
      "description": "<p>??? ??, ??, ??? ?? ????, ??? ??? ?? ? ??? ? ????. ?? ??? ?????, ?? ??? ?? ?? 1d8 + ??? ?? ???? ???? ??? ???. ??? ?? ???, ??? ?? ???, ??? ??? ??? ???. ?? ??? ?? ?? ??? ?? ?, ??, ??, ?? ?? ? ??? ??? ???? ? ? ????.</p>"
    },
    "Noodle Body": {
      "name": "Noodle 몸체"
    },
    "Obscuring Dream": {
      "name": "Obscuring 꿈",
      "description": "<p>? ???? @Compendium[dnd5e.spells.kSPRpeIx3w3nihrF]{Dream} ??? ? ? ??? ? ???, ? ??? ?? ? ? ??? ?????. ?? ??? ??? ?? ??? ??? ? ??? ??? ?? ????. ? ??? ?? ?? ?? ??? ?????.</p><p>Dream? ??? ?, ?? ???? ?? ??? ???? ?? ??, ???? ??? ???? ??? ??? ??? ??? ? ????. ??? ??? ??? ????? ??? ????? ????, ? ?? ? ??? ???? ?? ??? ????(?: ???? ??? ??? ?????) ? ??? ?????. ??? ??? ??? DC 8 + ??? ?? ??? + ??? ?? ???? ?? ?? ?? ??? ?? ???. ???? ?? ??? ?? ???? ? ?? ??? ???? ?????. ??? ? ??? ? ??, ? ? ??, ?? ??, ?? ?? ??? ??? ??? ???, ??? ? ?? ??? ???? ????.</p><p>?? ??? ????, ? ???? ?? 7? ?? ??? ?? 1?? ??? ???? ??? ???? ??? ???? ????. ?? ??? ???? ?? ????, ??? ???? ?? ?? ??? ?? ?? ??? ???. ?? ??? ???? ??? ??? ?? ???, ?? ??? ?? ??? ?? ? ??? ??? ? ????.</p>"
    },
    "Out of the Gate": {
      "name": "Out 의 - Gate"
    },
    "Powerful Build": {
      "name": "강인한 체격 - Powerful Build"
    },
    "Presence": {
      "description": "<p>?? ???? ??? ????? ???? ????, ????? ???? ???? ??? ??? ? ????. ????, ??? ??? 30?? ?? ????? DC 8 + ??? ?? ??? + ??? ?? ???? ?? ?? ?? ??? ?? ???. ???? ?? ??? ????? ??? ???, ? ???? ?? 24?? ?? ??? ???? ??? ???. ?? ??? ??? ?? ???? ?? 10? ?? ?? ?? ? ??? ??? ???. ? ??? ???? ? ??? ?? ??? ?? ??? ? ????.</p><ul><li><em><strong>??? ???</strong></em>. ??? ?? ? ??? ?????. ? ??? ?? ???? ?? ?? ?? ?? ????? ?? ?? ?? ?? ??? ???. ???? ??? ??? ?? ???? ??? ?? ???, ? ???? ?? ?? ?? ??? ? ? ????. ?? ??? ????, ? ???? ?? ? ??? ????.</li><li><em><strong>??? ???</strong></em>. ? ??? ???? ?? ???? ? ???? ??????. ??? ???? ????? ?? ? ?? ????. ? ??? ?? ???? ???? ????, ??? ???? ??? ?? ???? ????. 11??? ????, ???? ??? ??? ???? ??? ?? ?? ??? ??? ??? ??? ??? ??? ??? ? ????. ? ???? ??? ?? ?? ?? ?? ?, ??? ? ??? ?? ??? ?? ?? ??? ??? ????? ???? ???.</li></ul>"
    },
    "Prolonging Focus": {
      "name": "Prolonging 집중",
      "description": "<p>???? ??? ???? ?? ??? ???? ???? ??? ??? ???? ??? ???. ?? ??? ?? 1??? ??? ???? ???, ? ?? ??? ??? ? ????. ?? ??? ?? ?, <span style=\"font-family:var(--font-primary)\">DC 10 ?? ?? ??? ???. ???? ??? ???? ????. ??? ??? ??? ?? ???? ?? ??? ?????. ? ? 10???, ??? ??? 10?? 2? ???? DC(10? ? 12, 20? ? 14, ?? ?)? ?? ?? ?? ??? ???. ??? ??? ???? ????? ?? ??? ??? ??? ??? ?????.</span></p><p><span style=\"font-style:normal\">? ???? ??? ???? ??, ??? ????? ?? ?? ??? ???, ??? ??? ??? ???? ????. </span></p>"
    },
    "Rulers of Dragons": {
      "name": "Rulers 의 드래곤s"
    },
    "Slippery Thoughts": {
      "name": "Slippery 생각"
    },
    "Slow and Steady": {
      "name": "Slow 및 - Steady"
    },
    "Soil Sense": {
      "description": "<p><span style=\"font-family:Signika, sans-serif\">???? ??? ?? ???? ??? ???? ??? ??? ????. ??? ???? 1? ?? 15?? ??? ?? ??? ?? ? ????. ? ??? ???? ???? ???? ???? ? ? ???, ???? ??? ????. ? ??? ??? ??? ?? ???? ? ??? ?? ??? ?? ??? ? ????.</span><br class=\"Apple-interchange-newline\"></p>"
    },
    "Stackable Intellect": {
      "description": "<p>??? 60?? ?? ?? ??? ?? ?? ?? ?? ???? ????. ? ???? ??? ??? ?? ?? ?? ?????.</p><table style=\"width:100%\" border=\"1\"><tbody><tr><td style=\"width:100%\" colspan=\"2\"><p><span style=\"text-decoration:underline\"><strong><span style=\"text-decoration:underline\">??? ??</span></strong></span></p></td></tr><tr><td style=\"width:63.7094%;text-align:center\"><p>??? ?</p></td><td style=\"width:36.2906%;text-align:center\"><p>?? ?? ???</p></td></tr><tr><td style=\"width:63.7094%;text-align:center\"><p>2</p></td><td style=\"width:36.2906%;text-align:center\"><p>+1</p></td></tr><tr><td style=\"width:63.7094%;text-align:center\"><p>4</p></td><td style=\"width:36.2906%;text-align:center\"><p>+2</p></td></tr><tr><td style=\"width:63.7094%;text-align:center\"><p>8</p></td><td style=\"width:36.2906%;text-align:center\"><p>+3</p></td></tr><tr><td style=\"width:63.7094%;text-align:center\"><p>16</p></td><td style=\"width:36.2906%;text-align:center\"><p>+4</p></td></tr><tr><td style=\"width:63.7094%;text-align:center\"><p>32+</p></td><td style=\"width:36.2906%;text-align:center\"><p>+5</p></td></tr></tbody></table>"
    },
    "Survivable": {
      "description": "<p>?? ????. ??? ??? ??? ??? ? ? ?? ?? ?? ? ????.</p>"
    },
    "True Hearing": {
      "description": "<p><span class=\"fontstyle0\">??? ?? 2??? ??? ??? ???? ???? ??? ?? ? ????. 11??? ????, ???? ??? ??? ??? ??? ??? ?? ?? ????. ??? ?? ??? ?? ??? ? ?? ???, ?????? 300?? ??? ???? ??? ??? ?? ? ????. ? ??? ?? ???? ??? ??? ??? ?????, @Compendium[dnd5e.spells.5VhqFROQYjr1P9lp]{Silence} ??? ?????? ????.</span></p>"
    },
    "Unbroken Focus": {
      "name": "Unbroken 집중"
    },
    "Unshakable Guard": {
      "name": "Unshakable 수호"
    },
    "Venomous Claw": {
      "name": "Venomous 발톱",
      "description": "<p>??? ??? finesse ?????. ???? ?? ?? ???? ????? ???? ?, ?? ??? ?? ??? ??? ? ????. ?? ??? DC? 8 + ??? ?? ??? + ??? ?? ???? ????. ?? ??? ????, ? ???? ??? 1d12?? ?? ??? ?? 1?? ?? ?? ??? ???. ?? ??? ????, ?? ??? ?? ???? ????. 11??? ????, ?? ??? 5 ?? ??? ??? ? ???? ??? ?? ??? ????. ? ???? ??? ???, ??? ??? ??? ?? ?? ???? ?? ??? ?????. ? ??? ???? ?? ???? ? ??? ?? ??? ?? ??? ? ????.</p>"
    },
    "Voiceless Speech": {
      "description": "<p>?? ???? ???? ??? ??? ??, ?? ??? ???? ??? ?? ??? ?? ??? ??? ???? ????? ? ????. ??? ??? ??? ? ? ?? ?? ?? ???? ????? ? ??, ? ??? ?????.</p>"
    },
    "Vulpine Deduction": {
      "name": "여우류 - Deduction"
    },
    "Wings": {
      "name": "날개 - Wings"
    }
  }
}
